nonebot_plugin_mcsm/__init__.py
nonebot_plugin_mcsm/__main__.py
nonebot_plugin_mcsm/config.py
nonebot_plugin_mcsm/image.py
nonebot_plugin_mcsm/mcsm_api.py
nonebot_plugin_mcsm/model.py
nonebot_plugin_mcsm/static/icons/check-circle.svg
nonebot_plugin_mcsm/static/icons/cloud-server.svg
nonebot_plugin_mcsm/static/icons/info-circle.svg
nonebot_plugin_mcsm/static/templates/instance_info.css
nonebot_plugin_mcsm/static/templates/instance_info.html
nonebot_plugin_mcsm/static/templates/instance_list.css
nonebot_plugin_mcsm/static/templates/instance_list.html
nonebot_plugin_mcsm/static/templates/node_list.css
nonebot_plugin_mcsm/static/templates/node_list.html
nonebot_plugin_mcsm/static/templates/panel_info.css
nonebot_plugin_mcsm/static/templates/panel_info.html
nonebot_plugin_mcsm/utils.py
nonebot_plugin_mcsm-0.2.1.dist-info/WHEEL
nonebot_plugin_mcsm-0.2.1.dist-info/METADATA
nonebot_plugin_mcsm-0.2.1.dist-info/RECORD
