Metadata-Version: 2.1
Name: nonebot-plugin-mcsm
Version: 0.2.1
Summary: MCSM plugin for NoneBot2
Home-page: https://github.com/LiLuo-B/nonebot-plugin-mcsm
License: GPLv3
Author: LiLuo-B
Requires-Python: >=3.8,<4.0
Classifier: License :: Other/Proprietary License
Classifier: Programming Language :: Python :: 3
Classifier: Programming Language :: Python :: 3.10
Classifier: Programming Language :: Python :: 3.8
Classifier: Programming Language :: Python :: 3.9
Requires-Dist: httpx (>=0.13.0)
Requires-Dist: jinja2 (>=3.1.4)
Requires-Dist: nonebot-plugin-alconna (>=0.46.6)
Requires-Dist: nonebot-plugin-htmlrender (>=0.3.1)
Requires-Dist: nonebot2 (>=2.2.0)
Project-URL: Documentation, https://github.com/LiLuo-B/nonebot-plugin-mcsm/blob/main/README.md
Project-URL: Repository, https://github.com/LiLuo-B/nonebot-plugin-mcsm
